thermoflex/__init__.py
thermoflex/controls.py
thermoflex/devices.py
thermoflex/network.py
thermoflex/session_analyzer.py
thermoflex/sessions.py
thermoflex/tools/__init__.py
thermoflex/tools/debug.py
thermoflex/tools/nodeserial.py
thermoflex/tools/packet.py
thermoflex/tools/tfnode_messages_pb2.py
thermoflex/tools/test/nodetestingscript.py
thermoflex/tools/test/testcommands.py
thermoflex-1.0.1.dist-info/LICENSE.txt
thermoflex-1.0.1.dist-info/METADATA
thermoflex-1.0.1.dist-info/WHEEL
thermoflex-1.0.1.dist-info/top_level.txt
thermoflex-1.0.1.dist-info/RECORD
